spark_sight/__init__.py
spark_sight/create_charts/__init__.py
spark_sight/create_charts/parsing_spark_history_server.py
spark_sight/data_references.py
spark_sight/execute.py
spark_sight/log_parse/__init__.py
spark_sight/log_parse/main.py
spark_sight/log_transform/__init__.py
spark_sight/log_transform/main.py
spark_sight/util.py
spark_sight-0.1.11.dist-info/entry_points.txt
spark_sight-0.1.11.dist-info/WHEEL
spark_sight-0.1.11.dist-info/METADATA
spark_sight-0.1.11.dist-info/RECORD
