Metadata-Version: 2.1
Name: spark-sight
Version: 0.1.11
Summary: Spark performance at a glance
Author: Alfredo Fomitchenko
Author-email: alfredo.fomitchenko@mail.polimi.it
Requires-Python: >=3.6,<4.0
Classifier: Programming Language :: Python :: 3
Classifier: Programming Language :: Python :: 3.10
Classifier: Programming Language :: Python :: 3.6
Classifier: Programming Language :: Python :: 3.7
Classifier: Programming Language :: Python :: 3.8
Classifier: Programming Language :: Python :: 3.9
Requires-Dist: pandas (>=1.1,<=1.4.2)
Requires-Dist: plotly (>=5,<=5.7.0)
Requires-Dist: requests (<=2.27.1)
